Client/StreamlitClient.py
Client/WebsocketClient.py
Client/Utilities/OrderBookApp.py
Server/Server.py
Server/cli.py
Server/Exchanges/Abstract.py
Server/Exchanges/Binance.py
Server/Exchanges/CoinbasePro.py
Server/Exchanges/Exchange.py
Server/Exchanges/Kraken.py
Server/Exchanges/OKX.py
Server/Exchanges/__init__.py
Server/Utilities/Authentification.py
Server/Utilities/DataBaseManager.py
Server/Utilities/SubscriptionManager.py
Server/Utilities/SymbolFormatter.py
Server/Utilities/TWAPOrder.py
Server/Utilities/__init__.py
Server/Utilities/invalidated_tokens.json
Server/Utilities/users.db
multi_crypto_exchanges_api-1.1.15.dist-info/METADATA
multi_crypto_exchanges_api-1.1.15.dist-info/WHEEL
multi_crypto_exchanges_api-1.1.15.dist-info/entry_points.txt
multi_crypto_exchanges_api-1.1.15.dist-info/licenses/LICENSE
multi_crypto_exchanges_api-1.1.15.dist-info/RECORD
