Metadata-Version: 2.4
Name: multi-crypto-exchanges-api
Version: 1.1.15
Summary: Ce projet se compose d’une API côté serveur et d’une application client (Streamlit et WebSocket) permettant d’interagir avec plusieurs exchanges. L’API offre divers endpoints pour obtenir des données historiques, gérer l’authentification, exécuter des ordres (TWAP), streamer des carnets d'ordres, et bien plus encore.
License-File: LICENSE
Requires-Python: >=3.11
Requires-Dist: aiohttp>=3.11.11
Requires-Dist: fastapi>=0.115.8
Requires-Dist: ipykernel>=6.29.5
Requires-Dist: jinja2>=3.1.5
Requires-Dist: markupsafe==2.0.1
Requires-Dist: pandas>=2.2.3
Requires-Dist: plotly>=6.0.0
Requires-Dist: pyjwt>=2.10.1
Requires-Dist: requests>=2.32.3
Requires-Dist: sqlalchemy>=2.0.37
Requires-Dist: streamlit>=1.42.0
Requires-Dist: tabulate>=0.9.0
Requires-Dist: typer>=0.15.1
Requires-Dist: uv>=0.5.31
Requires-Dist: uvicorn>=0.34.0
Requires-Dist: websocket-client>=1.8.0
Requires-Dist: websockets>=14.2
